{"textures":[{"image":"2098-0.png","format":"RGBA8888","size":{"w":426,"h":215},"scale":1,"frames":[{"filename":"1_1_1","rotated":false,"trimmed":true,"sourceSize":{"w":1000,"h":1000},"spriteSourceSize":{"x":523,"y":386,"w":211,"h":156},"frame":{"x":1,"y":1,"w":211,"h":156}},{"filename":"2_1_1","rotated":false,"trimmed":true,"sourceSize":{"w":1000,"h":1000},"spriteSourceSize":{"x":498,"y":499,"w":247,"h":55},"frame":{"x":1,"y":159,"w":247,"h":55}},{"filename":"3_1_1","rotated":false,"trimmed":true,"sourceSize":{"w":1000,"h":1000},"spriteSourceSize":{"x":511,"y":394,"w":211,"h":156},"frame":{"x":214,"y":1,"w":211,"h":156}}]}],"meta":{"app":"https://www.codeandweb.com/texturepacker","version":"3.0","smartupdate":"$TexturePacker:SmartUpdate:1ee360df667fbb9be9ffb6a394add8ab:706570c4eb84523689d847611147730f:060d158cc3d03dbdf988e8dc7b5a6cac$"}}