{
	"generator_info": "Shape definitions generated with PhysicsEditor. Visit https://www.codeandweb.com/physicseditor",
	"walls": {
		"type": "fromPhysicsEditor",
		"label": "walls",
		"isStatic": false,
		"density": 0.1,
		"restitution": 0,
		"friction": 0.1,
		"frictionAir": 0.01,
		"frictionStatic": 0.5,
		"collisionFilter": {
			"group": 0,
			"category": 1,
			"mask": 255
		},
		"fixtures": [
			{
				"label": "",
				"isSensor": false,
				"vertices": [
					[ { "x":1433, "y":517 }, { "x":1413, "y":601 }, { "x":1531, "y":967 }, { "x":1551, "y":516 } ],
					[ { "x":1413, "y":601 }, { "x":1334, "y":827 }, { "x":1531, "y":967 } ],
					[ { "x":1544, "y":476 }, { "x":1531, "y":0 }, { "x":1423, "y":449 }, { "x":1434, "y":476 } ],
					[ { "x":1334, "y":827 }, { "x":1315, "y":860 }, { "x":1531, "y":967 } ],
					[ { "x":1315, "y":860 }, { "x":1282, "y":882 }, { "x":1531, "y":967 } ],
					[ { "x":1282, "y":882 }, { "x":506, "y":880 }, { "x":0, "y":967 }, { "x":1531, "y":967 } ],
					[ { "x":506, "y":880 }, { "x":64, "y":793 }, { "x":0, "y":967 } ],
					[ { "x":64, "y":793 }, { "x":64, "y":280 }, { "x":0, "y":0 }, { "x":0, "y":967 } ],
					[ { "x":64, "y":280 }, { "x":726, "y":248 }, { "x":1531, "y":0 }, { "x":0, "y":0 } ],
					[ { "x":726, "y":248 }, { "x":820, "y":311 }, { "x":1391, "y":424 }, { "x":1531, "y":0 } ],
					[ { "x":1391, "y":424 }, { "x":1423, "y":449 }, { "x":1531, "y":0 } ]
				]
			},
			{
				"label": "",
				"isSensor": false,
				"vertices": [
					[ { "x":1428, "y":556 }, { "x":1568, "y":537 }, { "x":1548, "y":457 }, { "x":1438, "y":462 } ]
				]
			}
		]
	},
	"nests": {
		"type": "fromPhysicsEditor",
		"label": "nests",
		"isStatic": false,
		"density": 0.1,
		"restitution": 0,
		"friction": 0.1,
		"frictionAir": 0.01,
		"frictionStatic": 0.5,
		"collisionFilter": {
			"group": 0,
			"category": 1,
			"mask": 255
		},
		"fixtures": [
			{
				"label": "",
				"isSensor": false,
				"vertices": [
					[ { "x":265, "y":-10 }, { "x":-15, "y":-10 }, { "x":-7, "y":402 }, { "x":169, "y":401 }, { "x":274, "y":319 } ]
				]
			}
		]
	},
	"trex_hq": {
		"type": "fromPhysicsEditor",
		"label": "trex_hq",
		"isStatic": false,
		"density": 0.10000000149011612,
		"restitution": 0,
		"friction": 0.10000000149011612,
		"frictionAir": 0.009999999776482582,
		"frictionStatic": 0.5,
		"collisionFilter": {
			"group": 0,
			"category": 1,
			"mask": 255
		},
		"fixtures": [
			{
				"label": "",
				"isSensor": false,
				"vertices": [
					[ { "x":799, "y":292 }, { "x":781, "y":-13 }, { "x":559, "y":-3 }, { "x":571, "y":294 } ]
				]
			}
		]
	},
	"pterodon": {
		"type": "fromPhysicsEditor",
		"label": "pterodon",
		"isStatic": false,
		"density": 0.10000000149011612,
		"restitution": 0,
		"friction": 0.10000000149011612,
		"frictionAir": 0.009999999776482582,
		"frictionStatic": 0.5,
		"collisionFilter": {
			"group": 0,
			"category": 1,
			"mask": 255
		},
		"fixtures": [
			{
				"label": "",
				"isSensor": false,
				"vertices": [
					[ { "x":1331, "y":583 }, { "x":1531, "y":583 }, { "x":1531, "y":0 }, { "x":1419, "y":1 }, { "x":1415, "y":12 }, { "x":1331, "y":358 } ]
				]
			}
		]
	},
	"game1": {
		"type": "fromPhysicsEditor",
		"label": "game1",
		"isStatic": false,
		"density": 0.1,
		"restitution": 0,
		"friction": 0.1,
		"frictionAir": 0.01,
		"frictionStatic": 0.5,
		"collisionFilter": {
			"group": 0,
			"category": 1,
			"mask": 255
		},
		"fixtures": [
			{
				"label": "",
				"isSensor": false,
				"vertices": [
					[ { "x":442, "y":484 }, { "x":493, "y":503 }, { "x":540, "y":510 }, { "x":609, "y":505 }, { "x":686, "y":485 }, { "x":546, "y":375 }, { "x":441, "y":405 }, { "x":433, "y":437 } ],
					[ { "x":681, "y":401 }, { "x":589, "y":375 }, { "x":546, "y":375 }, { "x":686, "y":485 }, { "x":697, "y":458 } ]
				]
			}
		]
	},
	"game2": {
		"type": "fromPhysicsEditor",
		"label": "game2",
		"isStatic": false,
		"density": 0.10000000149011612,
		"restitution": 0,
		"friction": 0.10000000149011612,
		"frictionAir": 0.009999999776482582,
		"frictionStatic": 0.5,
		"collisionFilter": {
			"group": 0,
			"category": 1,
			"mask": 255
		},
		"fixtures": [
			{
				"label": "",
				"isSensor": false,
				"vertices": [
					[ { "x":1052, "y":754 }, { "x":1103, "y":773 }, { "x":1150, "y":780 }, { "x":1219, "y":775 }, { "x":1296, "y":755 }, { "x":1156, "y":645 }, { "x":1051, "y":675 }, { "x":1043, "y":707 } ],
					[ { "x":1291, "y":671 }, { "x":1199, "y":645 }, { "x":1156, "y":645 }, { "x":1296, "y":755 }, { "x":1307, "y":728 } ]
				]
			}
		]
	}
}
