{
	"textures": [
		{
			"image": "11751@3x-0.png",
			"format": "RGBA8888",
			"size": {
				"w": 91,
				"h": 78
			},
			"scale": 0.5,
			"frames": [
				{
					"filename": "11751",
					"rotated": false,
					"trimmed": true,
					"sourceSize": {
						"w": 250,
						"h": 250
					},
					"spriteSourceSize": {
						"x": 82,
						"y": 95,
						"w": 89,
						"h": 76
					},
					"frame": {
						"x": 1,
						"y": 1,
						"w": 89,
						"h": 76
					}
				}
			]
		}
	],
	"meta": {
		"app": "https://www.codeandweb.com/texturepacker",
		"version": "3.0",
		"smartupdate": "$TexturePacker:SmartUpdate:b9da78f4748a8335642daaefbae7f7e4:32e6c1013be2e071ba7c906a2e4e8588:f673c9c8ae708ac0d7063af9da8bab6a$"
	}
}
