{
	"textures": [
		{
			"image": "14562@3x-0.png",
			"format": "RGBA8888",
			"size": {
				"w": 92,
				"h": 78
			},
			"scale": 0.5,
			"frames": [
				{
					"filename": "14562",
					"rotated": false,
					"trimmed": true,
					"sourceSize": {
						"w": 250,
						"h": 250
					},
					"spriteSourceSize": {
						"x": 81,
						"y": 95,
						"w": 90,
						"h": 76
					},
					"frame": {
						"x": 1,
						"y": 1,
						"w": 90,
						"h": 76
					}
				}
			]
		}
	],
	"meta": {
		"app": "https://www.codeandweb.com/texturepacker",
		"version": "3.0",
		"smartupdate": "$TexturePacker:SmartUpdate:f029568e1e98ee358edc9858b6b6b6dd:4bf6561485f55f84669856fbcf024ace:156d9ae769d24945f26c0542209e9ab3$"
	}
}
