{
	"textures": [
		{
			"image": "1530@4x-0.png",
			"format": "RGBA8888",
			"size": {
				"w": 166,
				"h": 102
			},
			"scale": 1,
			"frames": [
				{
					"filename": "1530",
					"rotated": false,
					"trimmed": true,
					"sourceSize": {
						"w": 500,
						"h": 500
					},
					"spriteSourceSize": {
						"x": 171,
						"y": 194,
						"w": 164,
						"h": 100
					},
					"frame": {
						"x": 1,
						"y": 1,
						"w": 164,
						"h": 100
					}
				}
			]
		}
	],
	"meta": {
		"app": "https://www.codeandweb.com/texturepacker",
		"version": "3.0",
		"smartupdate": "$TexturePacker:SmartUpdate:48edfd29a7069d2a0d8ca2f2055ff7be:d0bc3e8b99be1ce98190398cb37688fb:6e240e0706c6d708513e054a456668ca$"
	}
}
