{
	"textures": [
		{
			"image": "1567@4x-0.png",
			"format": "RGBA8888",
			"size": {
				"w": 143,
				"h": 164
			},
			"scale": 1,
			"frames": [
				{
					"filename": "1567",
					"rotated": false,
					"trimmed": true,
					"sourceSize": {
						"w": 500,
						"h": 500
					},
					"spriteSourceSize": {
						"x": 182,
						"y": 173,
						"w": 141,
						"h": 162
					},
					"frame": {
						"x": 1,
						"y": 1,
						"w": 141,
						"h": 162
					}
				}
			]
		}
	],
	"meta": {
		"app": "https://www.codeandweb.com/texturepacker",
		"version": "3.0",
		"smartupdate": "$TexturePacker:SmartUpdate:881b93c8647ec47822fed9875ed28966:a90584b5489706df72761df72e467be3:2ec80e2229388cb4d02da47b0ab62e5f$"
	}
}
