{
	"textures": [
		{
			"image": "1817@3x-0.png",
			"format": "RGBA8888",
			"size": {
				"w": 83,
				"h": 86
			},
			"scale": 0.5,
			"frames": [
				{
					"filename": "1817",
					"rotated": false,
					"trimmed": true,
					"sourceSize": {
						"w": 250,
						"h": 250
					},
					"spriteSourceSize": {
						"x": 84,
						"y": 83,
						"w": 81,
						"h": 84
					},
					"frame": {
						"x": 1,
						"y": 1,
						"w": 81,
						"h": 84
					}
				}
			]
		}
	],
	"meta": {
		"app": "https://www.codeandweb.com/texturepacker",
		"version": "3.0",
		"smartupdate": "$TexturePacker:SmartUpdate:e221f40effae3178f507f36ff1a1feb1:3933a59be2ebea31ab06a39f254c9e0d:cb9dc4ee66925270f6df833f84f30c39$"
	}
}
