{
	"textures": [
		{
			"image": "2173@4x-0.png",
			"format": "RGBA8888",
			"size": {
				"w": 147,
				"h": 154
			},
			"scale": 1,
			"frames": [
				{
					"filename": "2173",
					"rotated": false,
					"trimmed": true,
					"sourceSize": {
						"w": 500,
						"h": 500
					},
					"spriteSourceSize": {
						"x": 179,
						"y": 174,
						"w": 145,
						"h": 152
					},
					"frame": {
						"x": 1,
						"y": 1,
						"w": 145,
						"h": 152
					}
				}
			]
		}
	],
	"meta": {
		"app": "https://www.codeandweb.com/texturepacker",
		"version": "3.0",
		"smartupdate": "$TexturePacker:SmartUpdate:a779fdc5f2671c8dcf871ae5595cbd1f:fc766850f892a646bfe52516bd7fc95c:2f04d487229c1c27b8ba15e2cf5a62d8$"
	}
}
