{
	"textures": [
		{
			"image": "24153@3x-0.png",
			"format": "RGBA8888",
			"size": {
				"w": 82,
				"h": 62
			},
			"scale": 0.5,
			"frames": [
				{
					"filename": "24153",
					"rotated": false,
					"trimmed": true,
					"sourceSize": {
						"w": 250,
						"h": 250
					},
					"spriteSourceSize": {
						"x": 84,
						"y": 98,
						"w": 80,
						"h": 60
					},
					"frame": {
						"x": 1,
						"y": 1,
						"w": 80,
						"h": 60
					}
				}
			]
		}
	],
	"meta": {
		"app": "https://www.codeandweb.com/texturepacker",
		"version": "3.0",
		"smartupdate": "$TexturePacker:SmartUpdate:85b8adace3885187ec0cf644f104a059:810035c39afe6e4e1f5c46060508ff7b:3806157f4e7b21a818ace20db4475422$"
	}
}
