{
	"textures": [
		{
			"image": "24208@3x-0.png",
			"format": "RGBA8888",
			"size": {
				"w": 88,
				"h": 72
			},
			"scale": 0.5,
			"frames": [
				{
					"filename": "24208",
					"rotated": false,
					"trimmed": true,
					"sourceSize": {
						"w": 250,
						"h": 250
					},
					"spriteSourceSize": {
						"x": 82,
						"y": 93,
						"w": 86,
						"h": 70
					},
					"frame": {
						"x": 1,
						"y": 1,
						"w": 86,
						"h": 70
					}
				}
			]
		}
	],
	"meta": {
		"app": "https://www.codeandweb.com/texturepacker",
		"version": "3.0",
		"smartupdate": "$TexturePacker:SmartUpdate:1b2a07c09ba77fb4ef3fbd0c2910d48a:48d2af6ada257e6013aa4e6e7f2b152c:f9d1c20ff873fdc341176c02b1db8a91$"
	}
}
