{
	"textures": [
		{
			"image": "24249@3x-0.png",
			"format": "RGBA8888",
			"size": {
				"w": 88,
				"h": 62
			},
			"scale": 0.5,
			"frames": [
				{
					"filename": "24249",
					"rotated": false,
					"trimmed": true,
					"sourceSize": {
						"w": 250,
						"h": 250
					},
					"spriteSourceSize": {
						"x": 82,
						"y": 95,
						"w": 86,
						"h": 60
					},
					"frame": {
						"x": 1,
						"y": 1,
						"w": 86,
						"h": 60
					}
				}
			]
		}
	],
	"meta": {
		"app": "https://www.codeandweb.com/texturepacker",
		"version": "3.0",
		"smartupdate": "$TexturePacker:SmartUpdate:82da2010d860cba0da3a29ff2c3e7be6:39eddf7280543841c8c4264000646990:6e5d393af54a25d394442ef399fae2c2$"
	}
}
