{
	"textures": [
		{
			"image": "3020@3x-0.png",
			"format": "RGBA8888",
			"size": {
				"w": 84,
				"h": 87
			},
			"scale": 0.5,
			"frames": [
				{
					"filename": "3020",
					"rotated": false,
					"trimmed": true,
					"sourceSize": {
						"w": 250,
						"h": 250
					},
					"spriteSourceSize": {
						"x": 85,
						"y": 84,
						"w": 82,
						"h": 85
					},
					"frame": {
						"x": 1,
						"y": 1,
						"w": 82,
						"h": 85
					}
				}
			]
		}
	],
	"meta": {
		"app": "https://www.codeandweb.com/texturepacker",
		"version": "3.0",
		"smartupdate": "$TexturePacker:SmartUpdate:bfcafaf3d9d276898bcd2686700e374c:c7f0ea4e0030185dffbdfcc28334aa58:2c9dd5051621b9b34fbb7aaec0ec37c6$"
	}
}
