{
	"textures": [
		{
			"image": "4238@4x-0.png",
			"format": "RGBA8888",
			"size": {
				"w": 176,
				"h": 131
			},
			"scale": 1,
			"frames": [
				{
					"filename": "4238",
					"rotated": false,
					"trimmed": true,
					"sourceSize": {
						"w": 500,
						"h": 500
					},
					"spriteSourceSize": {
						"x": 163,
						"y": 180,
						"w": 174,
						"h": 129
					},
					"frame": {
						"x": 1,
						"y": 1,
						"w": 174,
						"h": 129
					}
				}
			]
		}
	],
	"meta": {
		"app": "https://www.codeandweb.com/texturepacker",
		"version": "3.0",
		"smartupdate": "$TexturePacker:SmartUpdate:14c7e6f55d4972c8147914703e74baa5:993f1befbef07054f10fd0f7f34522d6:8afe30336c26d128a1c785f55c914a86$"
	}
}
