{
	"textures": [
		{
			"image": "4418@3x-0.png",
			"format": "RGBA8888",
			"size": {
				"w": 66,
				"h": 83
			},
			"scale": 0.5,
			"frames": [
				{
					"filename": "4418",
					"rotated": false,
					"trimmed": true,
					"sourceSize": {
						"w": 250,
						"h": 250
					},
					"spriteSourceSize": {
						"x": 93,
						"y": 84,
						"w": 64,
						"h": 81
					},
					"frame": {
						"x": 1,
						"y": 1,
						"w": 64,
						"h": 81
					}
				}
			]
		}
	],
	"meta": {
		"app": "https://www.codeandweb.com/texturepacker",
		"version": "3.0",
		"smartupdate": "$TexturePacker:SmartUpdate:087ad4625c2a717d730858729ca4e79e:0e4a7564d6fbf44fe252ea0e65942dbb:968c37fe2e86e18b195b61dc5d4ca3ed$"
	}
}
