{
	"textures": [
		{
			"image": "4719@3x-0.png",
			"format": "RGBA8888",
			"size": {
				"w": 90,
				"h": 64
			},
			"scale": 0.5,
			"frames": [
				{
					"filename": "4719",
					"rotated": false,
					"trimmed": true,
					"sourceSize": {
						"w": 250,
						"h": 250
					},
					"spriteSourceSize": {
						"x": 81,
						"y": 94,
						"w": 88,
						"h": 62
					},
					"frame": {
						"x": 1,
						"y": 1,
						"w": 88,
						"h": 62
					}
				}
			]
		}
	],
	"meta": {
		"app": "https://www.codeandweb.com/texturepacker",
		"version": "3.0",
		"smartupdate": "$TexturePacker:SmartUpdate:0b90f92d082acd487b210225d777cd81:82f48f38ee7fb875e26f0a11ebfa2af5:9f3f6850997d6f119b7decbbf2560f8c$"
	}
}
