{
	"textures": [
		{
			"image": "4793@4x-0.png",
			"format": "RGBA8888",
			"size": {
				"w": 168,
				"h": 154
			},
			"scale": 1,
			"frames": [
				{
					"filename": "4793",
					"rotated": false,
					"trimmed": true,
					"sourceSize": {
						"w": 500,
						"h": 500
					},
					"spriteSourceSize": {
						"x": 169,
						"y": 170,
						"w": 166,
						"h": 152
					},
					"frame": {
						"x": 1,
						"y": 1,
						"w": 166,
						"h": 152
					}
				}
			]
		}
	],
	"meta": {
		"app": "https://www.codeandweb.com/texturepacker",
		"version": "3.0",
		"smartupdate": "$TexturePacker:SmartUpdate:074f1d049cb4cd345969de03f609c62d:b4b62e6e7218eea891508d52a41a5b12:3a9e00416a35260e901d8749cc4708bb$"
	}
}
