{
	"textures": [
		{
			"image": "640@3x-0.png",
			"format": "RGBA8888",
			"size": {
				"w": 83,
				"h": 57
			},
			"scale": 0.5,
			"frames": [
				{
					"filename": "640",
					"rotated": false,
					"trimmed": true,
					"sourceSize": {
						"w": 250,
						"h": 250
					},
					"spriteSourceSize": {
						"x": 86,
						"y": 98,
						"w": 81,
						"h": 55
					},
					"frame": {
						"x": 1,
						"y": 1,
						"w": 81,
						"h": 55
					}
				}
			]
		}
	],
	"meta": {
		"app": "https://www.codeandweb.com/texturepacker",
		"version": "3.0",
		"smartupdate": "$TexturePacker:SmartUpdate:c1809d33fa5df8bd1a59795891812814:7a0708b2c6cf818abe1aff3089e35dd2:7f3a987b22199a08da6925665d3b5775$"
	}
}
