{
	"textures": [
		{
			"image": "7002@3x-0.png",
			"format": "RGBA8888",
			"size": {
				"w": 88,
				"h": 84
			},
			"scale": 0.5,
			"frames": [
				{
					"filename": "7002",
					"rotated": false,
					"trimmed": true,
					"sourceSize": {
						"w": 250,
						"h": 250
					},
					"spriteSourceSize": {
						"x": 82,
						"y": 84,
						"w": 86,
						"h": 82
					},
					"frame": {
						"x": 1,
						"y": 1,
						"w": 86,
						"h": 82
					}
				}
			]
		}
	],
	"meta": {
		"app": "https://www.codeandweb.com/texturepacker",
		"version": "3.0",
		"smartupdate": "$TexturePacker:SmartUpdate:964a925326e476ffe83b1e0d1f042f04:399c234662727430f16450fe83d98575:ce841ee84653bcb8302e724b858af16c$"
	}
}
