{
	"textures": [
		{
			"image": "7204@4x-0.png",
			"format": "RGBA8888",
			"size": {
				"w": 101,
				"h": 117
			},
			"scale": 1,
			"frames": [
				{
					"filename": "7204",
					"rotated": false,
					"trimmed": true,
					"sourceSize": {
						"w": 500,
						"h": 500
					},
					"spriteSourceSize": {
						"x": 197,
						"y": 194,
						"w": 99,
						"h": 115
					},
					"frame": {
						"x": 1,
						"y": 1,
						"w": 99,
						"h": 115
					}
				}
			]
		}
	],
	"meta": {
		"app": "https://www.codeandweb.com/texturepacker",
		"version": "3.0",
		"smartupdate": "$TexturePacker:SmartUpdate:19456c5f5973447604cd2659ea1a456f:78e38c40e379c8948ea82c4bc21cf594:f01dddcc27c4dca862830ecfc31c9232$"
	}
}
