{
	"textures": [
		{
			"image": "771@4x-0.png",
			"format": "RGBA8888",
			"size": {
				"w": 150,
				"h": 96
			},
			"scale": 1,
			"frames": [
				{
					"filename": "771",
					"rotated": false,
					"trimmed": true,
					"sourceSize": {
						"w": 500,
						"h": 500
					},
					"spriteSourceSize": {
						"x": 176,
						"y": 215,
						"w": 148,
						"h": 94
					},
					"frame": {
						"x": 1,
						"y": 1,
						"w": 148,
						"h": 94
					}
				}
			]
		}
	],
	"meta": {
		"app": "https://www.codeandweb.com/texturepacker",
		"version": "3.0",
		"smartupdate": "$TexturePacker:SmartUpdate:4e6da23ae58f52333381f963489490b1:8e1356eb9f2f86e5d1b98b5dd075d5fb:25a5b92e6d660cfc926a9226f41234a3$"
	}
}
