{
	"textures": [
		{
			"image": "9020@3x-0.png",
			"format": "RGBA8888",
			"size": {
				"w": 81,
				"h": 85
			},
			"scale": 0.5,
			"frames": [
				{
					"filename": "9020",
					"rotated": false,
					"trimmed": true,
					"sourceSize": {
						"w": 250,
						"h": 250
					},
					"spriteSourceSize": {
						"x": 86,
						"y": 83,
						"w": 79,
						"h": 83
					},
					"frame": {
						"x": 1,
						"y": 1,
						"w": 79,
						"h": 83
					}
				}
			]
		}
	],
	"meta": {
		"app": "https://www.codeandweb.com/texturepacker",
		"version": "3.0",
		"smartupdate": "$TexturePacker:SmartUpdate:c78401374427c18c298749a189f03001:91ac17df65a0def2102756db787d18cb:fc380a155bfecb39a623f5d348e0b03d$"
	}
}
