{
	"textures": [
		{
			"image": "9083@4x-0.png",
			"format": "RGBA8888",
			"size": {
				"w": 157,
				"h": 165
			},
			"scale": 1,
			"frames": [
				{
					"filename": "9083",
					"rotated": false,
					"trimmed": true,
					"sourceSize": {
						"w": 500,
						"h": 500
					},
					"spriteSourceSize": {
						"x": 174,
						"y": 167,
						"w": 155,
						"h": 163
					},
					"frame": {
						"x": 1,
						"y": 1,
						"w": 155,
						"h": 163
					}
				}
			]
		}
	],
	"meta": {
		"app": "https://www.codeandweb.com/texturepacker",
		"version": "3.0",
		"smartupdate": "$TexturePacker:SmartUpdate:a5141f0f7365a15b28388a8b5eeb007d:f3f7d7c4210a90473030ed7e0298ec35:ba6271db43f5786ea0390e1e81f874e2$"
	}
}
