{
	"textures": [
		{
			"image": "1007@3x-0.png",
			"format": "RGBA8888",
			"size": {
				"w": 98,
				"h": 83
			},
			"scale": 0.5,
			"frames": [
				{
					"filename": "1007",
					"rotated": false,
					"trimmed": true,
					"sourceSize": {
						"w": 525,
						"h": 525
					},
					"spriteSourceSize": {
						"x": 215,
						"y": 172,
						"w": 96,
						"h": 81
					},
					"frame": {
						"x": 1,
						"y": 1,
						"w": 96,
						"h": 81
					}
				}
			]
		}
	],
	"meta": {
		"app": "https://www.codeandweb.com/texturepacker",
		"version": "3.0",
		"smartupdate": "$TexturePacker:SmartUpdate:7530151b47484dbcc3ba6f4fb74fce09:a47cdb33b8ab177789c9aa2514588362:4f7640e1f09d50d023f44359d70dca5a$"
	}
}
