{
	"textures": [
		{
			"image": "10276@4x-0.png",
			"format": "RGBA8888",
			"size": {
				"w": 466,
				"h": 264
			},
			"scale": 1,
			"frames": [
				{
					"filename": "10276",
					"rotated": false,
					"trimmed": true,
					"sourceSize": {
						"w": 1050,
						"h": 1050
					},
					"spriteSourceSize": {
						"x": 293,
						"y": 532,
						"w": 464,
						"h": 262
					},
					"frame": {
						"x": 1,
						"y": 1,
						"w": 464,
						"h": 262
					}
				}
			]
		}
	],
	"meta": {
		"app": "https://www.codeandweb.com/texturepacker",
		"version": "3.0",
		"smartupdate": "$TexturePacker:SmartUpdate:87d042f901086ced719b3be3690e27d5:db6071121d4fc9ae9124eba0b9d149d7:c0d680c3633b3bc88fa7e863ddba419f$"
	}
}
