{
	"textures": [
		{
			"image": "11203@4x-0.png",
			"format": "RGBA8888",
			"size": {
				"w": 255,
				"h": 181
			},
			"scale": 1,
			"frames": [
				{
					"filename": "11203",
					"rotated": false,
					"trimmed": true,
					"sourceSize": {
						"w": 1050,
						"h": 1050
					},
					"spriteSourceSize": {
						"x": 398,
						"y": 371,
						"w": 253,
						"h": 179
					},
					"frame": {
						"x": 1,
						"y": 1,
						"w": 253,
						"h": 179
					}
				}
			]
		}
	],
	"meta": {
		"app": "https://www.codeandweb.com/texturepacker",
		"version": "3.0",
		"smartupdate": "$TexturePacker:SmartUpdate:e07d1c249f6ee6ed8d7ba25f0448d437:4255ce4d9a5c5923d66613557399065d:daaf2bdc485839fab9674b5e136151b7$"
	}
}
