{
	"textures": [
		{
			"image": "1122@3x-0.png",
			"format": "RGBA8888",
			"size": {
				"w": 126,
				"h": 136
			},
			"scale": 0.5,
			"frames": [
				{
					"filename": "1122",
					"rotated": false,
					"trimmed": true,
					"sourceSize": {
						"w": 525,
						"h": 525
					},
					"spriteSourceSize": {
						"x": 198,
						"y": 174,
						"w": 124,
						"h": 134
					},
					"frame": {
						"x": 1,
						"y": 1,
						"w": 124,
						"h": 134
					}
				}
			]
		}
	],
	"meta": {
		"app": "https://www.codeandweb.com/texturepacker",
		"version": "3.0",
		"smartupdate": "$TexturePacker:SmartUpdate:590627556ff1e77235d3d04272dd3edc:0f9c104c0081b832bfe56ce842e261b6:defab6e19681831a941d43257187691f$"
	}
}
