{
	"textures": [
		{
			"image": "13020@3x-0.png",
			"format": "RGBA8888",
			"size": {
				"w": 175,
				"h": 148
			},
			"scale": 0.5,
			"frames": [
				{
					"filename": "13020",
					"rotated": false,
					"trimmed": true,
					"sourceSize": {
						"w": 525,
						"h": 525
					},
					"spriteSourceSize": {
						"x": 174,
						"y": 183,
						"w": 173,
						"h": 146
					},
					"frame": {
						"x": 1,
						"y": 1,
						"w": 173,
						"h": 146
					}
				}
			]
		}
	],
	"meta": {
		"app": "https://www.codeandweb.com/texturepacker",
		"version": "3.0",
		"smartupdate": "$TexturePacker:SmartUpdate:eff027bfc61c5c26082fe53cbc476727:e681f80a94e2222742538cc5cc3a6d19:d54d382bd0d43825f020d7f4629d5272$"
	}
}
