{
	"textures": [
		{
			"image": "14129@3x-0.png",
			"format": "RGBA8888",
			"size": {
				"w": 183,
				"h": 175
			},
			"scale": 0.5,
			"frames": [
				{
					"filename": "14129",
					"rotated": false,
					"trimmed": true,
					"sourceSize": {
						"w": 525,
						"h": 525
					},
					"spriteSourceSize": {
						"x": 173,
						"y": 222,
						"w": 181,
						"h": 173
					},
					"frame": {
						"x": 1,
						"y": 1,
						"w": 181,
						"h": 173
					}
				}
			]
		}
	],
	"meta": {
		"app": "https://www.codeandweb.com/texturepacker",
		"version": "3.0",
		"smartupdate": "$TexturePacker:SmartUpdate:dfde748c21e8a049f59ea2d44aff5df6:15bb11d07d68a2f3e2812ede6fddb60e:82321dcec5e7b807ed2db98b56f76cc1$"
	}
}
