{
	"textures": [
		{
			"image": "14932@4x-0.png",
			"format": "RGBA8888",
			"size": {
				"w": 349,
				"h": 223
			},
			"scale": 1,
			"frames": [
				{
					"filename": "14932",
					"rotated": false,
					"trimmed": true,
					"sourceSize": {
						"w": 1050,
						"h": 1050
					},
					"spriteSourceSize": {
						"x": 353,
						"y": 519,
						"w": 347,
						"h": 221
					},
					"frame": {
						"x": 1,
						"y": 1,
						"w": 347,
						"h": 221
					}
				}
			]
		}
	],
	"meta": {
		"app": "https://www.codeandweb.com/texturepacker",
		"version": "3.0",
		"smartupdate": "$TexturePacker:SmartUpdate:29c504ffd2b7b220e5453c58350fc1b7:501e24d543d8f5ab6ca588ad66be859d:8b16c9f9616556cb85ae5a922d880214$"
	}
}
