{
	"textures": [
		{
			"image": "2018@3x-0.png",
			"format": "RGBA8888",
			"size": {
				"w": 84,
				"h": 76
			},
			"scale": 0.5,
			"frames": [
				{
					"filename": "2018",
					"rotated": false,
					"trimmed": true,
					"sourceSize": {
						"w": 525,
						"h": 525
					},
					"spriteSourceSize": {
						"x": 221,
						"y": 195,
						"w": 82,
						"h": 74
					},
					"frame": {
						"x": 1,
						"y": 1,
						"w": 82,
						"h": 74
					}
				}
			]
		}
	],
	"meta": {
		"app": "https://www.codeandweb.com/texturepacker",
		"version": "3.0",
		"smartupdate": "$TexturePacker:SmartUpdate:a47d41b122cf59e4deef0ef5e3f2febc:c7246a7b569ea5388ed0bf334f1f60df:c30bb271e8de4ea169d98935cbb9134b$"
	}
}
