{
	"textures": [
		{
			"image": "2064@4x-0.png",
			"format": "RGBA8888",
			"size": {
				"w": 283,
				"h": 131
			},
			"scale": 1,
			"frames": [
				{
					"filename": "2064",
					"rotated": false,
					"trimmed": true,
					"sourceSize": {
						"w": 1050,
						"h": 1050
					},
					"spriteSourceSize": {
						"x": 442,
						"y": 374,
						"w": 281,
						"h": 129
					},
					"frame": {
						"x": 1,
						"y": 1,
						"w": 281,
						"h": 129
					}
				}
			]
		}
	],
	"meta": {
		"app": "https://www.codeandweb.com/texturepacker",
		"version": "3.0",
		"smartupdate": "$TexturePacker:SmartUpdate:40856f2f11e1c72f82bacec0c50fbecc:f202bfb144a3e006e2bcfa0a4a060f52:4f05c2cfdaa397ee9cf58f5c5df1c40b$"
	}
}
