{
	"textures": [
		{
			"image": "21056@4x-0.png",
			"format": "RGBA8888",
			"size": {
				"w": 169,
				"h": 122
			},
			"scale": 1,
			"frames": [
				{
					"filename": "21056",
					"rotated": false,
					"trimmed": true,
					"sourceSize": {
						"w": 1050,
						"h": 1050
					},
					"spriteSourceSize": {
						"x": 444,
						"y": 372,
						"w": 167,
						"h": 120
					},
					"frame": {
						"x": 1,
						"y": 1,
						"w": 167,
						"h": 120
					}
				}
			]
		}
	],
	"meta": {
		"app": "https://www.codeandweb.com/texturepacker",
		"version": "3.0",
		"smartupdate": "$TexturePacker:SmartUpdate:885814e2ec5ade1a06dab23bd6ab0c0c:18e0ebbce0ba32ff906147335be92614:8b6a34c90da24bcfb7ec421b1bb214d3$"
	}
}
