{
	"textures": [
		{
			"image": "3117@3x-0.png",
			"format": "RGBA8888",
			"size": {
				"w": 111,
				"h": 64
			},
			"scale": 0.5,
			"frames": [
				{
					"filename": "3117",
					"rotated": false,
					"trimmed": true,
					"sourceSize": {
						"w": 525,
						"h": 525
					},
					"spriteSourceSize": {
						"x": 206,
						"y": 257,
						"w": 109,
						"h": 62
					},
					"frame": {
						"x": 1,
						"y": 1,
						"w": 109,
						"h": 62
					}
				}
			]
		}
	],
	"meta": {
		"app": "https://www.codeandweb.com/texturepacker",
		"version": "3.0",
		"smartupdate": "$TexturePacker:SmartUpdate:0e5fb59fa0bc1299deb9469de430e017:2e37ede1568346eee652737bb0780d68:9a58d704b8d7253423732710d73d626f$"
	}
}
