{
	"textures": [
		{
			"image": "3186@3x-0.png",
			"format": "RGBA8888",
			"size": {
				"w": 216,
				"h": 90
			},
			"scale": 0.5,
			"frames": [
				{
					"filename": "3186",
					"rotated": false,
					"trimmed": true,
					"sourceSize": {
						"w": 525,
						"h": 525
					},
					"spriteSourceSize": {
						"x": 157,
						"y": 253,
						"w": 214,
						"h": 88
					},
					"frame": {
						"x": 1,
						"y": 1,
						"w": 214,
						"h": 88
					}
				}
			]
		}
	],
	"meta": {
		"app": "https://www.codeandweb.com/texturepacker",
		"version": "3.0",
		"smartupdate": "$TexturePacker:SmartUpdate:208b1e7741bec964b67e290f121f14e7:2c047dd004853a14776cb19ea465ec5a:1f85a39981758773339ff81cd813fb32$"
	}
}
