{
	"textures": [
		{
			"image": "34235@4x-0.png",
			"format": "RGBA8888",
			"size": {
				"w": 174,
				"h": 50
			},
			"scale": 1,
			"frames": [
				{
					"filename": "34235",
					"rotated": false,
					"trimmed": true,
					"sourceSize": {
						"w": 1050,
						"h": 1050
					},
					"spriteSourceSize": {
						"x": 441,
						"y": 464,
						"w": 172,
						"h": 48
					},
					"frame": {
						"x": 1,
						"y": 1,
						"w": 172,
						"h": 48
					}
				}
			]
		}
	],
	"meta": {
		"app": "https://www.codeandweb.com/texturepacker",
		"version": "3.0",
		"smartupdate": "$TexturePacker:SmartUpdate:cbe1b81f87ce713b2839b2485444c960:048fabb791b6543cfedefbf1418ee307:193151bc95d646225da466ce18cda376$"
	}
}
