{
	"textures": [
		{
			"image": "4039@3x-0.png",
			"format": "RGBA8888",
			"size": {
				"w": 235,
				"h": 241
			},
			"scale": 0.5,
			"frames": [
				{
					"filename": "4039",
					"rotated": false,
					"trimmed": true,
					"sourceSize": {
						"w": 525,
						"h": 525
					},
					"spriteSourceSize": {
						"x": 146,
						"y": 165,
						"w": 233,
						"h": 239
					},
					"frame": {
						"x": 1,
						"y": 1,
						"w": 233,
						"h": 239
					}
				}
			]
		}
	],
	"meta": {
		"app": "https://www.codeandweb.com/texturepacker",
		"version": "3.0",
		"smartupdate": "$TexturePacker:SmartUpdate:15074b3d2547c2f71c87c3b6039876bf:cd34cd42168b52fdd1d9eb21296f7cdb:d4388a0279df43e714d3a5b893b29538$"
	}
}
