{
	"textures": [
		{
			"image": "4259@3x-0.png",
			"format": "RGBA8888",
			"size": {
				"w": 211,
				"h": 123
			},
			"scale": 0.5,
			"frames": [
				{
					"filename": "4259",
					"rotated": false,
					"trimmed": true,
					"sourceSize": {
						"w": 525,
						"h": 525
					},
					"spriteSourceSize": {
						"x": 159,
						"y": 257,
						"w": 209,
						"h": 121
					},
					"frame": {
						"x": 1,
						"y": 1,
						"w": 209,
						"h": 121
					}
				}
			]
		}
	],
	"meta": {
		"app": "https://www.codeandweb.com/texturepacker",
		"version": "3.0",
		"smartupdate": "$TexturePacker:SmartUpdate:2babebaa061a44ba1e5f1ab616bc7ee7:f6462fff3f018aedbbc52eac09a7aa58:4629c830b87145df89cc15fd2bba58d8$"
	}
}
