{
	"textures": [
		{
			"image": "9058@4x-0.png",
			"format": "RGBA8888",
			"size": {
				"w": 423,
				"h": 424
			},
			"scale": 1,
			"frames": [
				{
					"filename": "1-1",
					"rotated": false,
					"trimmed": true,
					"sourceSize": {
						"w": 700,
						"h": 700
					},
					"spriteSourceSize": {
						"x": 9,
						"y": 9,
						"w": 421,
						"h": 422
					},
					"frame": {
						"x": 1,
						"y": 1,
						"w": 421,
						"h": 422
					}
				}
			]
		}
	],
	"meta": {
		"app": "https://www.codeandweb.com/texturepacker",
		"version": "3.0",
		"smartupdate": "$TexturePacker:SmartUpdate:b850c6b0c3fc8b3b150b6835fabd90a1:3eb3078f5862f019f177436358d7a8d5:57b7f863f47daa941aa05274264662a1$"
	}
}
