{
	"textures": [
		{
			"image": "9281@3x-0.png",
			"format": "RGBA8888",
			"size": {
				"w": 214,
				"h": 214
			},
			"scale": 0.5,
			"frames": [
				{
					"filename": "1-1",
					"rotated": false,
					"trimmed": true,
					"sourceSize": {
						"w": 350,
						"h": 350
					},
					"spriteSourceSize": {
						"x": 4,
						"y": 4,
						"w": 212,
						"h": 212
					},
					"frame": {
						"x": 1,
						"y": 1,
						"w": 212,
						"h": 212
					}
				}
			]
		}
	],
	"meta": {
		"app": "https://www.codeandweb.com/texturepacker",
		"version": "3.0",
		"smartupdate": "$TexturePacker:SmartUpdate:c29c57380a040bceb1da202567d30600:98dafb333f8ca9ec96ee1b92bde1a3c2:45ce4bb33eaca6c16cd4e069be3d15c6$"
	}
}
