{
	"textures": [
		{
			"image": "1042@4x-0.png",
			"format": "RGBA8888",
			"size": {
				"w": 80,
				"h": 98
			},
			"scale": 1,
			"frames": [
				{
					"filename": "1-1",
					"rotated": false,
					"trimmed": true,
					"sourceSize": {
						"w": 1520,
						"h": 960
					},
					"spriteSourceSize": {
						"x": 719,
						"y": 433,
						"w": 78,
						"h": 96
					},
					"frame": {
						"x": 1,
						"y": 1,
						"w": 78,
						"h": 96
					}
				}
			]
		}
	],
	"meta": {
		"app": "https://www.codeandweb.com/texturepacker",
		"version": "3.0",
		"smartupdate": "$TexturePacker:SmartUpdate:bb8a968939fa9f4f017c6011e841b7ea:79036bd6c73b1f638b7cc9883c64c9b4:54ef29b4a74a31f6985bf1b2219addcf$"
	}
}
