{
	"textures": [
		{
			"image": "2258@4x-0.png",
			"format": "RGBA8888",
			"size": {
				"w": 92,
				"h": 111
			},
			"scale": 1,
			"frames": [
				{
					"filename": "1-1",
					"rotated": false,
					"trimmed": true,
					"sourceSize": {
						"w": 1520,
						"h": 960
					},
					"spriteSourceSize": {
						"x": 716,
						"y": 427,
						"w": 90,
						"h": 109
					},
					"frame": {
						"x": 1,
						"y": 1,
						"w": 90,
						"h": 109
					}
				}
			]
		}
	],
	"meta": {
		"app": "https://www.codeandweb.com/texturepacker",
		"version": "3.0",
		"smartupdate": "$TexturePacker:SmartUpdate:d5026bb05ec2b59117e71b86e36090a1:19eee07489d04c65aee08c9dfa0fb634:4dee438d86b54ccc9e2dac6bb9839aa2$"
	}
}
