{
	"textures": [
		{
			"image": "835@3x-0.png",
			"format": "RGBA8888",
			"size": {
				"w": 58,
				"h": 39
			},
			"scale": 0.5,
			"frames": [
				{
					"filename": "1-1",
					"rotated": false,
					"trimmed": true,
					"sourceSize": {
						"w": 760,
						"h": 480
					},
					"spriteSourceSize": {
						"x": 352,
						"y": 221,
						"w": 56,
						"h": 37
					},
					"frame": {
						"x": 1,
						"y": 1,
						"w": 56,
						"h": 37
					}
				}
			]
		}
	],
	"meta": {
		"app": "https://www.codeandweb.com/texturepacker",
		"version": "3.0",
		"smartupdate": "$TexturePacker:SmartUpdate:0a0883b6f38d6434b37bfdf6e3abc57e:7534ceca75228677e95b350ea8722e69:d3c87c91142784916d4411adc8cdaaea$"
	}
}
