{
	"textures": [
		{
			"image": "34413@4x-0.png",
			"format": "RGBA8888",
			"size": {
				"w": 158,
				"h": 95
			},
			"scale": 1,
			"frames": [
				{
					"filename": "34413",
					"rotated": false,
					"trimmed": true,
					"sourceSize": {
						"w": 500,
						"h": 500
					},
					"spriteSourceSize": {
						"x": 175,
						"y": 200,
						"w": 158,
						"h": 95
					},
					"frame": {
						"x": 0,
						"y": 0,
						"w": 158,
						"h": 95
					}
				}
			]
		}
	],
	"meta": {
		"app": "https://www.codeandweb.com/texturepacker",
		"version": "3.0",
		"smartupdate": "$TexturePacker:SmartUpdate:27b5920d4e561b29c805c12a8fffb869:376febc55cff36730ca54551055c5ba6:6ad8eca8372615ff8a6ab9d97fb2cd51$"
	}
}
